setup.cfg
setup.py
dplython/__init__.py
dplython/dplython.py
dplython/test.py
dplython.egg-info/PKG-INFO
dplython.egg-info/SOURCES.txt
dplython.egg-info/dependency_links.txt
dplython.egg-info/requires.txt
dplython.egg-info/top_level.txt
dplython/data/__init__.py
dplython/data/diamonds.csv