Metadata-Version: 1.1
Name: dplython
Version: 0.0.4
Summary: Dplyr-style operations on top of pandas DataFrame.
Home-page: https://github.com/dodger487/dplython
Author: Chris Riederer
Author-email: OfficialChrisEmail@gmail.com
License: MIT
Download-URL: https://github.com/dodger487/dplython/tarball/0.0.4
Keywords: pandas data dplyr
Platform: UNKNOWN
Classifier: Development Status :: 3 - Alpha
Classifier: Intended Audience :: Developers
Classifier: Intended Audience :: Science/Research
Classifier: License :: OSI Approved :: MIT License
Classifier: Environment :: Web Environment
Classifier: Operating System :: OS Independent
Classifier: Programming Language :: Python :: 2.7
Classifier: Programming Language :: Python :: 3.3
Classifier: Programming Language :: Python :: 3.4
Classifier: Programming Language :: Python :: 3.5
Classifier: Topic :: Scientific/Engineering
